keytitan/__init__.py
keytitan/__main__.py
keytitan/keytitan.py
keytitan-1.0.0.dist-info/LICENSE
keytitan-1.0.0.dist-info/METADATA
keytitan-1.0.0.dist-info/WHEEL
keytitan-1.0.0.dist-info/top_level.txt
keytitan-1.0.0.dist-info/RECORD
