Metadata-Version: 2.1
Name: keytitan
Version: 1.0.0
Summary: Create and validate strong password
Author-email: Suryansh Pandey <suryanshp1@gmail.com>
License: The MIT License (MIT)
Keywords: security,password,authentication
Classifier: License :: OSI Approved :: MIT License
Classifier: Programming Language :: Python
Classifier: Programming Language :: Python :: 3
Requires-Python: >=3.9
License-File: LICENSE
Requires-Dist: tomli ; python_version < "3.11"
Provides-Extra: dev
Requires-Dist: black ; extra == 'dev'
Requires-Dist: bumpver ; extra == 'dev'
Requires-Dist: isort ; extra == 'dev'
Requires-Dist: pip-tools ; extra == 'dev'
